tauk/__init__.py
tauk/__main__.py
tauk/api.py
tauk/config.py
tauk/enums.py
tauk/exceptions.py
tauk/log_formatter.py
tauk/tauk_webdriver.py
tauk/utils.py
tauk/assistant/__init__.py
tauk/assistant/assistant.py
tauk/assistant/config.py
tauk/context/__init__.py
tauk/context/context.py
tauk/context/test_case.py
tauk/context/test_data.py
tauk/context/test_error.py
tauk/context/test_suite.py
tauk/listeners/__init__.py
tauk/listeners/unittest_listener.py
tauk/listeners/unittest_multiprocess_listener.py
tests/__init__.py
tests/utils.py
tests/e2e/__init__.py
tests/e2e/custom_integration_support.py
tests/e2e/custom_integration_test.py
tests/e2e/listeners/__init__.py
tests/e2e/listeners/multiprocess/__init__.py
tests/e2e/listeners/multiprocess/launcher.py
tests/e2e/listeners/multiprocess/main.py
tests/e2e/listeners/multiprocess/test_one.py
tests/e2e/listeners/multiprocess/test_two.py
tauk-2.1.3.dist-info/LICENSE
tauk-2.1.3.dist-info/METADATA
tauk-2.1.3.dist-info/WHEEL
tauk-2.1.3.dist-info/top_level.txt
tauk-2.1.3.dist-info/RECORD
