Metadata-Version: 2.1
Name: tauk
Version: 2.1.3
Summary: Helper package to facilitate reporting for webdriver-based tests on Tauk
Home-page: https://github.com/thetauk/tauk-webdriver-python
Author: Nathan Krishnan
License: MIT License
Platform: ALL
Classifier: Programming Language :: Python :: 3
Classifier: License :: OSI Approved :: MIT License
Classifier: Operating System :: OS Independent
License-File: LICENSE
Requires-Dist: requests
Requires-Dist: filelock
Requires-Dist: jsonpickle
Requires-Dist: tzlocal
Requires-Dist: python-json-logger
Requires-Dist: tqdm
